poetry_assembly/__init__.py
poetry_assembly/assembly.py
poetry_assembly/setup_template.py
poetry_assembly-0.1.0.dist-info/METADATA
poetry_assembly-0.1.0.dist-info/WHEEL
poetry_assembly-0.1.0.dist-info/entry_points.txt
poetry_assembly-0.1.0.dist-info/RECORD
