Metadata-Version: 2.1
Name: poetry_assembly
Version: 0.1.0
Summary: 
Author: qingqinzhan
Author-email: qingqinzhan@tencent.com
Requires-Python: >=3.8,<4.0
Classifier: Programming Language :: Python :: 3
Classifier: Programming Language :: Python :: 3.8
Classifier: Programming Language :: Python :: 3.9
Classifier: Programming Language :: Python :: 3.10
Classifier: Programming Language :: Python :: 3.11
Requires-Dist: shshsh (>=1.0.4,<2.0.0)
